LICENSE.txt
MANIFEST.in
README.md
setup.cfg
setup.py
oscar_portation.egg-info/PKG-INFO
oscar_portation.egg-info/SOURCES.txt
oscar_portation.egg-info/SOURCES.txt.py
oscar_portation.egg-info/dependency_links.txt
oscar_portation.egg-info/dependency_links.txt.py
oscar_portation.egg-info/requires.txt
oscar_portation.egg-info/requires.txt.py
oscar_portation.egg-info/top_level.txt
oscar_portation.egg-info/top_level.txt.py
portation/__init__.py
portation/app.py
portation/base.py
portation/config.py
portation/exporters.py
portation/forms.py
portation/importers.py
portation/views.py
portation/locale/bg/LC_MESSAGES/django.mo
portation/locale/bg/LC_MESSAGES/django.po
portation/locale/cs/LC_MESSAGES/django.mo
portation/locale/cs/LC_MESSAGES/django.po
portation/locale/de/LC_MESSAGES/django.mo
portation/locale/de/LC_MESSAGES/django.po
portation/locale/en/LC_MESSAGES/django.mo
portation/locale/en/LC_MESSAGES/django.po
portation/locale/es/LC_MESSAGES/django.mo
portation/locale/es/LC_MESSAGES/django.po
portation/locale/fr/LC_MESSAGES/django.mo
portation/locale/fr/LC_MESSAGES/django.po
portation/locale/uk/LC_MESSAGES/django.mo
portation/locale/uk/LC_MESSAGES/django.po
portation/templates/portation/base.html